{
  "baseTheme": "Spain and Latin America — colonial, pre-Columbian, and traditional settings",
  "palette": "Warm sunset tones — burnt orange, terracotta red, golden yellow, turquoise, deep crimson",
  "settings": [
    { "anchor": "Mediterranean fishing port at dawn", "zone": "coastal" },
    { "anchor": "Caribbean harbor in tropical storm", "zone": "coastal" },
    { "anchor": "rocky Atlantic lighthouse at dusk", "zone": "coastal" },
    { "anchor": "salt flats shimmering at midday", "zone": "coastal" },
    { "anchor": "Andean terraced village in fog", "zone": "mountain" },
    { "anchor": "Sierra Nevada goat trail at sunset", "zone": "mountain" },
    { "anchor": "volcanic ridge above jungle canopy", "zone": "mountain" },
    { "anchor": "highland monastery in frost", "zone": "mountain" },
    { "anchor": "olive grove at harvest time", "zone": "rural" },
    { "anchor": "agave field under blazing sun", "zone": "rural" },
    { "anchor": "vineyard at grape-crushing time", "zone": "rural" },
    { "anchor": "cattle ranch at dawn", "zone": "rural" },
    { "anchor": "coffee plantation in morning mist", "zone": "rural" },
    { "anchor": "Seville flamenco cellar at midnight", "zone": "urban" },
    { "anchor": "Mexico City market in rain", "zone": "urban" },
    { "anchor": "colonial plaza at siesta hour", "zone": "urban" },
    { "anchor": "Moorish courtyard with central fountain", "zone": "urban" },
    { "anchor": "Buenos Aires tango hall at dusk", "zone": "urban" },
    { "anchor": "hacienda kitchen with hanging chiles", "zone": "interior" },
    { "anchor": "monastery scriptorium with illuminated texts", "zone": "interior" },
    { "anchor": "wine cellar with oak barrels", "zone": "interior" },
    { "anchor": "tile workshop with glazing kilns", "zone": "interior" },
    { "anchor": "apothecary with bundled herbs", "zone": "interior" },
    { "anchor": "Day of the Dead altar in candlelight", "zone": "spiritual" },
    { "anchor": "cathedral nave with stained glass", "zone": "spiritual" },
    { "anchor": "desert pilgrimage road at sunset", "zone": "spiritual" },
    { "anchor": "jungle cenote ceremony at dawn", "zone": "spiritual" },
    { "anchor": "fiesta with fireworks overhead", "zone": "seasonal" },
    { "anchor": "dusty harvest in golden light", "zone": "seasonal" },
    { "anchor": "monsoon flooding a cobblestone street", "zone": "seasonal" },
    { "anchor": "wildflower meadow in spring", "zone": "seasonal" },
    { "anchor": "scorching desert noon with heat waves", "zone": "seasonal" },
    { "anchor": "blacksmith forging ironwork gates", "zone": "craft" },
    { "anchor": "pottery wheel in sun-baked courtyard", "zone": "craft" },
    { "anchor": "loom weaving serape patterns", "zone": "craft" },
    { "anchor": "leather tooling workshop", "zone": "craft" },
    { "anchor": "glassblowing furnace at night", "zone": "craft" },
    { "anchor": "jungle river rapids", "zone": "water" },
    { "anchor": "fishing boat on glacial Patagonian lake", "zone": "water" },
    { "anchor": "ancient aqueduct spanning a valley", "zone": "water" }
  ],
  "elementCategories": {
    "people": ["matador", "flamenco dancer", "conquistador", "farmer", "shepherd", "priest", "artisan", "fisherman", "gaucho", "merchant", "guitar player", "healer", "weaver", "miner", "scribe"],
    "flora": ["bougainvillea", "agave", "cactus", "jacaranda", "oleander", "palm", "marigold", "hibiscus", "orchid", "sunflower", "olive tree", "grape vine", "corn stalk", "pepper plant"],
    "objects": ["guitar", "castanets", "clay pot", "woven basket", "leather saddle", "stone mortar", "silver cross", "wooden cart", "clay tile", "rope lasso", "hammock", "ceramic jug", "hand fan", "iron bell"],
    "animals": ["bull", "eagle", "iguana", "parrot", "armadillo", "llama", "donkey", "rooster", "jaguar", "condor", "snake", "hummingbird", "goat", "lizard"],
    "architecture": ["adobe wall", "terracotta arch", "wrought-iron balcony", "tiled fountain", "stone pyramid steps", "bell tower", "wooden shutters", "cobblestone alley", "courtyard colonnade", "mission wall", "vine-covered pergola", "clay chimney"],
    "lighting": ["torch flame", "oil lantern", "candle cluster", "fireplace glow", "desert sunlight", "bonfire", "stained glass light", "moonlight", "furnace glow", "starlight"],
    "weather": ["dust devil", "tropical rain", "blazing heat", "cool evening breeze", "morning dew", "fog", "thunder clouds", "hail", "rainbow after storm", "dry wind"],
    "sensory": ["guitar strum", "church bells", "sizzling food", "rooster crow", "distant drumming", "flowing fountain", "crackling fire", "ocean waves"]
  },
  "elementKeywords": [
    "plaza", "hacienda", "adobe", "terracotta", "flamenco", "guitar", "bull",
    "matador", "cathedral", "mission", "conquistador", "marigold", "cactus",
    "agave", "sombrero", "serape", "tortilla", "mercado", "fiesta", "siesta",
    "courtyard", "fountain", "bougainvillea", "palm", "olive", "vineyard",
    "monastery", "pyramid", "cenote", "jungle", "desert", "tango", "gaucho",
    "condor", "llama", "jaguar", "parrot", "armadillo", "iguana", "donkey",
    "iron gate", "tile", "pottery", "leather", "lasso", "hammock", "bonfire",
    "torch", "candle", "stained glass", "bell tower", "cobblestone", "arch",
    "colonnade", "balcony", "shutters", "harvest", "corn", "pepper", "chile"
  ],
  "artStyles": [
    "Talavera hand-painted tile patterns in cobalt blue and marigold yellow",
    "bold Diego Rivera mural style with flat planes and earthy worker figures",
    "Frida Kahlo surrealist portrait style with vivid tropical colors",
    "Baroque colonial altarpiece with gold and deep crimson",
    "Aztec codex illustration with geometric angular figures",
    "Moorish arabesque pattern with intricate interlocking geometry",
    "Huichol yarn painting with psychedelic neon beadwork dots",
    "Oaxacan alebrije folk art with fantastical creature forms",
    "Spanish Romantic oil painting with dramatic chiaroscuro shadows",
    "Mediterranean ceramic glaze in turquoise and terracotta",
    "Mayan stone relief carving with weathered limestone texture",
    "Day of the Dead papel picado cutout in vivid orange and purple",
    "gaucho leatherwork tooling with warm brown and burnt sienna",
    "Chilean arpillera textile with patchwork fabric texture",
    "flamenco poster art with bold red and black silhouettes"
  ]
}
